nonebot_plugin_hammer_core/__init__.py
nonebot_plugin_hammer_core/util/__init__.py
nonebot_plugin_hammer_core/util/constant.py
nonebot_plugin_hammer_core/util/message_factory.py
nonebot_plugin_hammer_core/util/onebot_utils.py
nonebot_plugin_hammer_core-0.3.3.dist-info/LICENSE
nonebot_plugin_hammer_core-0.3.3.dist-info/METADATA
nonebot_plugin_hammer_core-0.3.3.dist-info/WHEEL
nonebot_plugin_hammer_core-0.3.3.dist-info/RECORD
