Metadata-Version: 2.1
Name: nonebot-plugin-hammer-core
Version: 0.3.3
Summary: core dependency of nonebot-plugin-hammer-xxx
Home-page: https://docs.hammer-hfut.tk:233
License: Apache-2.0
Author: ArgonarioD
Author-email: 739062975@qq.com
Requires-Python: >=3.9,<4.0
Classifier: License :: OSI Approved :: Apache Software License
Classifier: Programming Language :: Python :: 3
Classifier: Programming Language :: Python :: 3.9
Classifier: Programming Language :: Python :: 3.10
Classifier: Programming Language :: Python :: 3.11
Requires-Dist: nonebot-adapter-onebot (>=2.3.0,<3.0.0)
Project-URL: Repository, https://github.com/ArgonarioD/nonebot-plugin-hammer-core
